hltb_pkg/HowLongToBeatEntry.py
hltb_pkg/HtmlScraper.py
hltb_pkg/__init__.py
hltbapi/HowLongToBeatEntry.py
hltbapi/HtmlScraper.py
hltbapi/__init__.py
HowLongToBeat_Python_API-0.1.14.dist-info/LICENSE
HowLongToBeat_Python_API-0.1.14.dist-info/METADATA
HowLongToBeat_Python_API-0.1.14.dist-info/WHEEL
HowLongToBeat_Python_API-0.1.14.dist-info/top_level.txt
HowLongToBeat_Python_API-0.1.14.dist-info/RECORD
