Metadata-Version: 2.1
Name: HowLongToBeat-Python-API
Version: 0.1.14
Summary: This package helps to get data from howlongtobeat.com
Home-page: https://github.com/JaeguKim/HowLongToBeat-Python-API
Author: KimWithGlasses
Author-email: kimwithglasses@kakao.com
License: UNKNOWN
Platform: UNKNOWN
Classifier: Programming Language :: Python :: 3
Classifier: License :: OSI Approved :: MIT License
Classifier: Operating System :: OS Independent
Requires-Python: >=3.6
Requires-Dist: urllib3
Requires-Dist: bs4 (>=0.0.1)
